<?xml version="1.0" encoding="UTF-8"?>
<objects serializationModel="Studio.01.08.00">
    <object class="AudioFile" id="{8ebd63d6-6f49-4693-97fc-0d41fbf6b36a}">
        <property name="assetPath">
            <value>taikoHit1.wav</value>
        </property>
        <property name="frequencyInKHz">
            <value>44.0999985</value>
        </property>
        <property name="channelCount">
            <value>2</value>
        </property>
        <property name="length">
            <value>3</value>
        </property>
        <relationship name="masterAssetFolder">
            <destination>{98ac971c-4b09-479e-88f3-982c4549c77a}</destination>
        </relationship>
    </object>
</objects>
